asfpy/__init__.py
asfpy/asfpy.py
asfpy_aridyckovsky-0.3.1.dist-info/LICENSE
asfpy_aridyckovsky-0.3.1.dist-info/METADATA
asfpy_aridyckovsky-0.3.1.dist-info/WHEEL
asfpy_aridyckovsky-0.3.1.dist-info/top_level.txt
asfpy_aridyckovsky-0.3.1.dist-info/RECORD
