Metadata-Version: 2.1
Name: asfpy-aridyckovsky
Version: 0.3.1
Summary: A collection of Python scripts for the Application Statement Feedback Program's logistics needs
Home-page: https://github.com/aridyckovsky/asfpy
Author: Ari Dyckovsky
Author-email: aridyckovsky@gmail.com
License: UNKNOWN
Platform: UNKNOWN
Classifier: Programming Language :: Python :: 3
Classifier: License :: OSI Approved :: MIT License
Classifier: Operating System :: OS Independent
Requires-Python: >=3.6
